parishad/__init__.py
parishad/__main__.py
parishad/checker/__init__.py
parishad/checker/deterministic.py
parishad/checker/ensemble.py
parishad/checker/retrieval.py
parishad/cli/__init__.py
parishad/cli/code.py
parishad/cli/main.py
parishad/cli/prarambh.py
parishad/cli/sthapana.py
parishad/config/modes.py
parishad/config/pipeline.core.yaml
parishad/config/pipeline.extended.yaml
parishad/config/pipeline.fast.yaml
parishad/config/user_config.py
parishad/data/catalog.py
parishad/data/models.json
parishad/memory/__init__.py
parishad/models/__init__.py
parishad/models/costs.py
parishad/models/downloader.py
parishad/models/optimizations.py
parishad/models/profiles.py
parishad/models/reliability.py
parishad/models/runner.py
parishad/models/tokenization.py
parishad/models/backends/__init__.py
parishad/models/backends/base.py
parishad/models/backends/huggingface.py
parishad/models/backends/llama_cpp.py
parishad/models/backends/mlx_lm.py
parishad/models/backends/ollama.py
parishad/models/backends/openai_api.py
parishad/models/backends/transformers_hf.py
parishad/orchestrator/__init__.py
parishad/orchestrator/config_loader.py
parishad/orchestrator/engine.py
parishad/orchestrator/exceptions.py
parishad/roles/__init__.py
parishad/roles/base.py
parishad/roles/dandadhyaksha.py
parishad/roles/darbari.py
parishad/roles/majumdar.py
parishad/roles/pantapradhan.py
parishad/roles/prerak.py
parishad/roles/raja.py
parishad/roles/sacheev.py
parishad/roles/sainik.py
parishad/roles/sar_senapati.py
parishad/roles/vidushak.py
parishad/tools/__init__.py
parishad/tools/base.py
parishad/tools/fs.py
parishad/tools/perception.py
parishad/tools/retrieval.py
parishad/tools/shell.py
parishad/utils/__init__.py
parishad/utils/hardware.py
parishad/utils/installer.py
parishad/utils/logging.py
parishad/utils/scanner.py
parishad/utils/text.py
parishad/utils/tracing.py
parishad-0.1.7.dist-info/METADATA
parishad-0.1.7.dist-info/WHEEL
parishad-0.1.7.dist-info/entry_points.txt
parishad-0.1.7.dist-info/licenses/LICENSE
parishad-0.1.7.dist-info/RECORD
