Metadata-Version: 2.4
Name: parishad
Version: 0.1.7
Summary: A cost-aware, local-first council of heterogeneous LLMs for reliable reasoning, coding, and factual correctness
Project-URL: Homepage, https://github.com/parishad-council/parishad
Project-URL: Documentation, https://github.com/parishad-council/parishad#readme
Project-URL: Repository, https://github.com/parishad-council/parishad
Project-URL: Issues, https://github.com/parishad-council/parishad/issues
Author: Parishad Team
License-Expression: MIT
License-File: LICENSE
Keywords: code-generation,council,llm,local-llm,multi-agent,reasoning
Classifier: Development Status :: 3 - Alpha
Classifier: Intended Audience :: Developers
Classifier: Intended Audience :: Science/Research
Classifier: License :: OSI Approved :: MIT License
Classifier: Programming Language :: Python :: 3
Classifier: Programming Language :: Python :: 3.10
Classifier: Programming Language :: Python :: 3.11
Classifier: Programming Language :: Python :: 3.12
Classifier: Topic :: Scientific/Engineering :: Artificial Intelligence
Requires-Python: >=3.10
Requires-Dist: click>=8.0.0
Requires-Dist: httpx>=0.25.0
Requires-Dist: jsonschema>=4.0.0
Requires-Dist: numpy<2.0
Requires-Dist: openai>=1.0.0
Requires-Dist: psutil>=5.9.0
Requires-Dist: pydantic-settings>=2.0.0
Requires-Dist: pydantic>=2.0.0
Requires-Dist: pyyaml>=6.0
Requires-Dist: rich>=13.0.0
Requires-Dist: textual>=0.70.0
Requires-Dist: tiktoken>=0.5.0
Provides-Extra: all
Requires-Dist: accelerate>=0.25.0; extra == 'all'
Requires-Dist: black>=23.0.0; extra == 'all'
Requires-Dist: chromadb>=0.5.0; extra == 'all'
Requires-Dist: datasets>=2.14.0; extra == 'all'
Requires-Dist: faiss-cpu>=1.7.0; extra == 'all'
Requires-Dist: llama-cpp-python>=0.2.0; extra == 'all'
Requires-Dist: mypy>=1.0.0; extra == 'all'
Requires-Dist: pandas>=2.0.0; extra == 'all'
Requires-Dist: pre-commit>=3.0.0; extra == 'all'
Requires-Dist: pypdf>=3.0.0; extra == 'all'
Requires-Dist: ruff>=0.1.0; extra == 'all'
Requires-Dist: sentence-transformers>=2.2.0; extra == 'all'
Requires-Dist: torch>=2.0.0; extra == 'all'
Requires-Dist: tqdm>=4.66.0; extra == 'all'
Requires-Dist: transformers>=4.35.0; extra == 'all'
Provides-Extra: benchmark
Requires-Dist: datasets>=2.14.0; extra == 'benchmark'
Requires-Dist: pandas>=2.0.0; extra == 'benchmark'
Requires-Dist: tqdm>=4.66.0; extra == 'benchmark'
Provides-Extra: cuda
Requires-Dist: accelerate>=0.25.0; extra == 'cuda'
Requires-Dist: auto-gptq>=0.6.0; extra == 'cuda'
Requires-Dist: autoawq>=0.1.0; extra == 'cuda'
Requires-Dist: bitsandbytes>=0.41.0; extra == 'cuda'
Requires-Dist: optimum>=1.16.0; extra == 'cuda'
Requires-Dist: protobuf>=4.0.0; extra == 'cuda'
Requires-Dist: torch>=2.0.0; extra == 'cuda'
Requires-Dist: transformers>=4.35.0; extra == 'cuda'
Provides-Extra: dev
Requires-Dist: black>=23.0.0; extra == 'dev'
Requires-Dist: mypy>=1.0.0; extra == 'dev'
Requires-Dist: pre-commit>=3.0.0; extra == 'dev'
Requires-Dist: ruff>=0.1.0; extra == 'dev'
Provides-Extra: distributed
Requires-Dist: grpcio-tools>=1.50.0; extra == 'distributed'
Requires-Dist: grpcio>=1.50.0; extra == 'distributed'
Provides-Extra: local
Requires-Dist: accelerate>=0.25.0; extra == 'local'
Requires-Dist: llama-cpp-python>=0.2.0; extra == 'local'
Requires-Dist: torch>=2.0.0; extra == 'local'
Requires-Dist: transformers>=4.35.0; extra == 'local'
Provides-Extra: mlx
Requires-Dist: mlx-lm>=0.1.0; extra == 'mlx'
Provides-Extra: perception
Requires-Dist: markitdown>=0.0.1; extra == 'perception'
Provides-Extra: retrieval
Requires-Dist: chromadb>=0.5.0; extra == 'retrieval'
Requires-Dist: faiss-cpu>=1.7.0; extra == 'retrieval'
Requires-Dist: pypdf>=3.0.0; extra == 'retrieval'
Requires-Dist: sentence-transformers>=2.2.0; extra == 'retrieval'
